brute_curvefit/__init__.py
brute_curvefit/brute_curvefit.py
brute_curvefit-0.0.4.dist-info/LICENSE
brute_curvefit-0.0.4.dist-info/METADATA
brute_curvefit-0.0.4.dist-info/WHEEL
brute_curvefit-0.0.4.dist-info/top_level.txt
brute_curvefit-0.0.4.dist-info/RECORD
