Metadata-Version: 2.1
Name: brute-curvefit
Version: 0.0.4
Summary: Curve fitting using both brute force and scipy.optimize
Home-page: https://github.com/analkumar2/brute_force
Author: Anal Kumar
Author-email: analkumar2@gmail.com
License: UNKNOWN
Platform: UNKNOWN
Classifier: Programming Language :: Python :: 3
Classifier: License :: OSI Approved :: MIT License
Classifier: Operating System :: OS Independent
Requires-Python: >=3.6
